{
    "title": {
        "property": null,
        "language": "en"
    },
    "altern": {
        "property": null,
        "language": "en"
    },
    "creato": {
        "property": null,
        "language": "en"
    },
    "contri": {
        "property": null,
        "language": "en"
    },
    "publis": {
        "property": null,
        "language": "en"
    },
    "date": {
        "property": null,
        "language": "en"
    },
    "datea": {
        "property": null,
        "language": "en"
    },
    "sort": {
        "property": null,
        "language": "en"
    },
    "descri": {
        "property": null,
        "language": "en"
    },
    "extent": {
        "property": null,
        "language": "en"
    },
    "theme": {
        "property": null,
        "language": "en"
    },
    "coverb": {
        "property": null,
        "language": "en"
    },
    "subjec": {
        "property": null,
        "language": "en"
    },
    "resour": {
        "property": null,
        "language": "en"
    },
    "permis": {
        "property": null,
        "language": "en"
    },
    "format": {
        "property": null,
        "language": "en"
    },
    "langua": {
        "property": null,
        "language": "en"
    },
    "notes": {
        "property": null,
        "language": "en"
    },
    "call": {
        "property": null,
        "language": "en"
    },
    "access": {
        "property": null,
        "language": "en"
    },
    "digita": {
        "property": null,
        "language": "en"
    },
    "chung": {
        "property": null,
        "language": "en"
    },
    "covera": {
        "property": null,
        "language": "en"
    },
    "dateb": {
        "property": null,
        "language": "en"
    },
    "publia": {
        "property": null,
        "language": "en"
    },
    "rights": {
        "property": null,
        "language": "en"
    },
    "licens": {
        "property": null,
        "language": "en"
    },
    "transc": {
        "property": null,
        "language": "en"
    },
    "catalo": {
        "property": null,
        "language": "en"
    },
    "projec": {
        "property": null,
        "language": "en"
    },
    "aip": {
        "property": null,
        "language": "en"
    },
    "varian": {
        "property": null,
        "language": "en"
    },
    "variaa": {
        "property": null,
        "language": "en"
    },
    "variab": {
        "property": null,
        "language": "en"
    },
    "doi": {
        "property": null,
        "language": "en"
    },
    "fullrs": {
        "property": null,
        "language": "en"
    },
    "dmoclcno": {
        "property": null,
        "language": "en"
    },
    "dmcreated": {
        "property": null,
        "language": "en"
    },
    "dmmodified": {
        "property": null,
        "language": "en"
    },
    "dmrecord": {
        "property": null,
        "language": "en"
    },
    "find": {
        "property": null,
        "language": "en"
    }
}